MANIFEST.in
README.md
requirements.txt
setup.cfg
setup.py
sermos_utils/__init__.py
sermos_utils/constants.py
sermos_utils/deploy.py
sermos_utils/rho_model.py
sermos_utils/sermos_yaml.py
sermos_utils/utils.py
sermos_utils.egg-info/PKG-INFO
sermos_utils.egg-info/SOURCES.txt
sermos_utils.egg-info/dependency_links.txt
sermos_utils.egg-info/entry_points.txt
sermos_utils.egg-info/requires.txt
sermos_utils.egg-info/top_level.txt
sermos_utils/cli/__init__.py
sermos_utils/cli/deploy.py
sermos_utils/cli/rho_model.py
tests/fixtures/__init__.py