Metadata-Version: 2.1
Name: sermos-utils
Version: 0.22.1
Summary: Sermos Utilities
Home-page: https://bitbucket.org/rhoai/sermos-utils
Maintainer: Rho AI
License: MIT
Platform: UNKNOWN
Provides-Extra: test
Provides-Extra: docs
Provides-Extra: dev
